{
	"configurations" : 
	[
		{
			"directories" : 
			[
				{
					"build" : ".",
					"hasInstallRule" : true,
					"jsonFile" : "directory-.-Debug-1ff0530b3e4c756d7934.json",
					"minimumCMakeVersion" : 
					{
						"string" : "3.16"
					},
					"projectIndex" : 0,
					"source" : ".",
					"targetIndexes" : 
					[
						0,
						1,
						2
					]
				}
			],
			"name" : "Debug",
			"projects" : 
			[
				{
					"directoryIndexes" : 
					[
						0
					],
					"name" : "HexagonalMap",
					"targetIndexes" : 
					[
						0,
						1,
						2
					]
				}
			],
			"targets" : 
			[
				{
					"directoryIndex" : 0,
					"id" : "HexagonalMap::@6890427a1f51a3e7e1df",
					"jsonFile" : "target-HexagonalMap-Debug-f1402cd53c8982ca841f.json",
					"name" : "HexagonalMap",
					"projectIndex" : 0
				},
				{
					"directoryIndex" : 0,
					"id" : "HexagonalMap_autogen::@6890427a1f51a3e7e1df",
					"jsonFile" : "target-HexagonalMap_autogen-Debug-f5d0514f05b6f48ad721.json",
					"name" : "HexagonalMap_autogen",
					"projectIndex" : 0
				},
				{
					"directoryIndex" : 0,
					"id" : "HexagonalMap_autogen_timestamp_deps::@6890427a1f51a3e7e1df",
					"jsonFile" : "target-HexagonalMap_autogen_timestamp_deps-Debug-cd81fb93107a5676b170.json",
					"name" : "HexagonalMap_autogen_timestamp_deps",
					"projectIndex" : 0
				}
			]
		}
	],
	"kind" : "codemodel",
	"paths" : 
	{
		"build" : "/media/yauheni/A88AF9F78AF9C23C/Hexagonal Map/HexagonalMap/Hex/build-src-Desktop_Qt_6_6_1_GCC_64bit-Debug",
		"source" : "/media/yauheni/A88AF9F78AF9C23C/Hexagonal Map/HexagonalMap/Hex/src"
	},
	"version" : 
	{
		"major" : 2,
		"minor" : 6
	}
}
